DataDocking/__init__.py
DataDocking/data_restframework.py
DataDocking-0.0.3.dist-info/LICENSE
DataDocking-0.0.3.dist-info/METADATA
DataDocking-0.0.3.dist-info/WHEEL
DataDocking-0.0.3.dist-info/top_level.txt
DataDocking-0.0.3.dist-info/RECORD
