Metadata-Version: 2.1
Name: DataDocking
Version: 0.0.3
Summary: Data Docking package
Home-page: https://github.com/AlitaIcon/DataDocking
Author: alita
Author-email: 1906321518@qq.com
License: MIT
Project-URL: Documentation, https://github.com/AlitaIcon/DataDocking
Project-URL: Source, https://pypi.org/project/DataDocking/
Platform: UNKNOWN
Classifier: Programming Language :: Python :: 3
Classifier: License :: OSI Approved :: MIT License
Classifier: Operating System :: OS Independent
Requires-Python: >=3.6
Requires-Dist: records (>=0.5.3)
